hlsvdpro/__init__.py
hlsvdpro/_cpropack.so
hlsvdpro/_dpropack.so
hlsvdpro/_spropack.so
hlsvdpro/_zpropack.so
hlsvdpro/hlsvd.py
hlsvdpro/propack.py
hlsvdpro/simple_test.py
hlsvdpro-2.0.0.dist-info/LICENSE
hlsvdpro-2.0.0.dist-info/METADATA
hlsvdpro-2.0.0.dist-info/WHEEL
hlsvdpro-2.0.0.dist-info/top_level.txt
hlsvdpro-2.0.0.dist-info/RECORD
