Metadata-Version: 2.1
Name: hlsvdpro
Version: 2.0.0
Summary: HLSVDPRO provides code to fit a model function (sum of lorentzians) to time-domain data via a 'black box' state space approach. This is often used in clinical MRS to remove residual water from time domain signals. 
Home-page: http://scion.duhs.duke.edu/projects/hlsvdpro
Author: Brian J. Soher
Author-email: bsoher@briansoher.com
Maintainer: Brian J. Soher
Maintainer-email: bsoher@briansoher.com
License: https://opensource.org/licenses/BSD-3-Clause
Keywords: svd,hlsvd,hlsvdpro,propack,time domain,fitting
Platform: Linux
Platform: OS X
Platform: Windows
Platform: POSIX
Classifier: Development Status :: 5 - Production/Stable
Classifier: Intended Audience :: Science/Research
Classifier: License :: OSI Approved :: BSD License
Classifier: Operating System :: MacOS :: MacOS X
Classifier: Operating System :: POSIX :: Linux
Classifier: Operating System :: Microsoft :: Windows
Classifier: Operating System :: Unix
Requires-Dist: setuptools
